LICENSE
py3status_github_notifications/__init__.py
py3status_github_notifications/github_notifications.py
py3status_github_notifications-0.1.6.dist-info/entry_points.txt
py3status_github_notifications-0.1.6.dist-info/LICENSE
py3status_github_notifications-0.1.6.dist-info/WHEEL
py3status_github_notifications-0.1.6.dist-info/METADATA
py3status_github_notifications-0.1.6.dist-info/RECORD
