Metadata-Version: 2.1
Name: py3status-github-notifications
Version: 0.1.6
Summary: py3status module to show your Github notifications
Home-page: https://github.com/mcgillij/py3status-github-notifications
License: MIT
Keywords: github,notifications,py3status,i3,git
Author: mcgillij
Author-email: mcgillivray.jason@gmail.com
Requires-Python: >=3.9,<4.0
Classifier: Environment :: X11 Applications
Classifier: Intended Audience :: End Users/Desktop
Classifier: License :: OSI Approved :: MIT License
Classifier: Operating System :: POSIX :: Linux
Classifier: Programming Language :: Python :: 3
Classifier: Programming Language :: Python :: 3.10
Classifier: Programming Language :: Python :: 3.9
Classifier: Topic :: Desktop Environment :: Window Managers
Classifier: Topic :: Software Development :: Version Control :: Git
Classifier: Topic :: System :: Monitoring
Requires-Dist: PyGithub (>=1.55,<2.0)
Requires-Dist: PyJWT (==2.5.0)
Requires-Dist: py3status (>=3.45,<4.0)
Project-URL: Documentation, https://github.com/mcgillij/py3status-github-notifications
Project-URL: Repository, https://github.com/mcgillij/py3status-github-notifications
